evkafka/__init__.py
evkafka/app.py
evkafka/config.py
evkafka/consumer.py
evkafka/context.py
evkafka/dependencies.py
evkafka/exceptions.py
evkafka/handle.py
evkafka/handler.py
evkafka/lifespan.py
evkafka/middleware.py
evkafka/producer.py
evkafka/py.typed
evkafka/sender.py
evkafka/state.py
evkafka/testclient.py
evkafka/types.py
evkafka/utils.py
evkafka-0.7.0.dist-info/LICENSE
evkafka-0.7.0.dist-info/METADATA
evkafka-0.7.0.dist-info/NOTICE.md
evkafka-0.7.0.dist-info/WHEEL
evkafka-0.7.0.dist-info/top_level.txt
evkafka-0.7.0.dist-info/RECORD
