Metadata-Version: 2.1
Name: evkafka
Version: 0.7.0
Summary: EVKafka framework. Handle kafka events easy
Author-email: Aleksey Katichev <theleharo@gmail.com>
Project-URL: Homepage, https://github.com/theleharo/evkafka
Project-URL: Bug Tracker, https://github.com/theleharo/evkafka/issues
Classifier: Development Status :: 3 - Alpha
Classifier: Intended Audience :: Developers
Classifier: Intended Audience :: Information Technology
Classifier: License :: OSI Approved :: MIT License
Classifier: Operating System :: Unix
Classifier: Programming Language :: Python :: 3 :: Only
Classifier: Programming Language :: Python :: 3.10
Classifier: Programming Language :: Python :: 3.11
Classifier: Topic :: Software Development :: Libraries :: Application Frameworks
Classifier: Topic :: Software Development :: Libraries :: Python Modules
Classifier: Typing :: Typed
Requires-Python: >=3.10
License-File: LICENSE
License-File: NOTICE.md
Requires-Dist: aiokafka ==0.8.1
Requires-Dist: aiohttp >=3.8.6
Requires-Dist: pydantic >=2.4.2
